LICENSE
validargs/__init__.py
validargs/exceptions.py
validargs/validargs.py
validargs-0.1.1.dist-info/LICENSE
validargs-0.1.1.dist-info/WHEEL
validargs-0.1.1.dist-info/METADATA
validargs-0.1.1.dist-info/RECORD
