Metadata-Version: 2.1
Name: validargs
Version: 0.1.1
Summary: Custom argument validation, injected directly in the function signature.
Home-page: https://github.com/kolitiri/validargs
License: MIT
Keywords: validation,valid,arguments,args,parameters
Author: christos.liontos
Author-email: christos.liontos.pr@gmail.com
Requires-Python: >=3.8,<4.0
Classifier: License :: OSI Approved :: MIT License
Classifier: Operating System :: OS Independent
Classifier: Programming Language :: Python :: 3
Classifier: Programming Language :: Python :: 3.8
Classifier: Programming Language :: Python :: 3.9
Classifier: Programming Language :: Python :: 3.10
Classifier: Topic :: Software Development :: Libraries :: Python Modules
Project-URL: Repository, https://github.com/kolitiri/validargs
